optimize_images/__init__.py
optimize_images/__main__.py
optimize_images/api.py
optimize_images/argument_parser.py
optimize_images/constants.py
optimize_images/data_structures.py
optimize_images/do_optimization.py
optimize_images/exceptions.py
optimize_images/file_utils.py
optimize_images/img_aux_processing.py
optimize_images/img_dynamic_quality.py
optimize_images/img_info.py
optimize_images/img_optimize_jpg.py
optimize_images/img_optimize_png.py
optimize_images/platforms.py
optimize_images/reporting.py
optimize_images/watch.py
optimize_images-1.5.1.dist-info/LICENSE
optimize_images-1.5.1.dist-info/METADATA
optimize_images-1.5.1.dist-info/WHEEL
optimize_images-1.5.1.dist-info/entry_points.txt
optimize_images-1.5.1.dist-info/top_level.txt
optimize_images-1.5.1.dist-info/RECORD
