Metadata-Version: 2.1
Name: optimize-images
Version: 1.5.1
Summary: A command-line interface (CLI) utility written in pure Python to help you reduce the file size of images.
Home-page: https://no-title.victordomingos.com/projects/optimize-images/
Author: Victor Domingos
License: MIT
Project-URL: Documentation, https://github.com/victordomingos/optimize-images/blob/master/docs/docs_EN.md
Project-URL: Source, https://github.com/victordomingos/optimize-images
Project-URL: Bug Reports, https://github.com/victordomingos/optimize-images/issues
Keywords: python3 pythonista-ios pil pillow image-processing image-compression image-optimization image-optimisation seo seo-optimization website-performance cli recursive non-recursive
Platform: UNKNOWN
Classifier: Development Status :: 4 - Beta
Classifier: Environment :: Console
Classifier: Intended Audience :: Developers
Classifier: Intended Audience :: Information Technology
Classifier: License :: OSI Approved :: MIT License
Classifier: Natural Language :: English
Classifier: Operating System :: OS Independent
Classifier: Operating System :: iOS
Classifier: Operating System :: MacOS :: MacOS X
Classifier: Operating System :: Microsoft :: Windows
Classifier: Operating System :: Unix
Classifier: Operating System :: POSIX :: Linux 
Classifier: Programming Language :: Python :: 3
Classifier: Programming Language :: Python :: 3.6
Classifier: Programming Language :: Python :: 3.7
Classifier: Programming Language :: Python :: 3.8
Classifier: Programming Language :: Python :: 3.9
Classifier: Programming Language :: Python :: 3.10
Classifier: Programming Language :: Python :: 3.11
Classifier: Topic :: Utilities
Classifier: Topic :: Multimedia :: Graphics
Classifier: Topic :: Multimedia :: Graphics :: Graphics Conversion
Requires-Python: >=3.7
License-File: LICENSE
Requires-Dist: piexif (>=1.1.3)
Requires-Dist: Pillow (>=8.2.0)
Requires-Dist: watchdog (>=2.1.2)
